{
	"rows": [
		{
			"default": {
				"modifier": "{roll:traits/face/looks/goodModifier}",
				"quality": "{roll:traits/face/looks/good}"
			},
			"weight": 6
		},
		{
			"default": {
				"quality": "{roll:traits/face/looks/good}"
			},
			"weight": 14
		},
		{
			"default": {
				"modifier": "{roll:traits/face/looks/badModifier}",
				"quality": "{roll:traits/face/looks/bad}"
			},
			"weight": 4
		},
		{
			"default": {
				"quality": "{roll:traits/face/looks/bad}"
			},
			"weight": 10
		},
		{
			"default": {
				"modifier": "{roll:traits/face/looks/normalModifier}",
				"quality": "{roll:traits/face/looks/normal}"
			},
			"weight": 8
		},
		{
			"default": {
				"quality": "{roll:traits/face/looks/normal}"
			},
			"weight": 30
		}
	],
	"values": {}
}