{
    "rows": [
        {
            "value": "", 
            "weight": 18
        }, 
        {
            "value": "$majPro", 
            "weight": 3
        }, 
        {
            "value": "$majPro", 
            "weight": 3
        }, 
        {
            "value": "$majPro", 
            "weight": 3
        }, 
        {
            "value": "$majPro", 
            "weight": 2
        }, 
        {
            "value": "$majPro", 
            "weight": 2
        }, 
        {
            "value": "$majPro", 
            "weight": 2
        }, 
        {
            "value": "$majPro", 
            "weight": 3
        }, 
        {
            "value": "$majPro", 
            "weight": 2
        }, 
        {
            "value": "$majPro", 
            "weight": 2
        }, 
        {
            "value": "$majPoss", 
            "weight": 3
        }
    ], 
    "values": {
        "$majPoss": "{$quirks+sentences are always ponctuated with seemingly random sounds. }", 
        "$majPro": "{$quirks+is often found staring at the sky. }"
    }
}