{
	"rows": [
		{
			"value": "$(identity.pronouns.singular) seeks to spread misery and despair."
		},
		{
			"value": "$(identity.pronouns.singular) seeks to spread lies and fear.",
			"modifiers": {
				"stats.abilityScore.intelligence": 3
			}
		},
		{
			"value": "$(identity.pronouns.singular) seeks to spread sadness and sorrow."
		},
		{
			"value": "$(identity.pronouns.singular) seeks to raise an army of followers.",
			"modifiers": {
				"stats.abilityScore.charisma": 2
			}
		},
		{
			"value": "$(identity.pronouns.singular) seeks to eradicate good aasimars."
		},
		{
			"value": "$(identity.pronouns.singular) seeks to eradicate followers of good gods."
		},
		{
			"value": "$(identity.pronouns.singular) seeks mindless destruction.",
			"modifiers": {
				"stats.alignmentTendancies.ethical.negative": 3
			}
		}
	],
	"values": {}
}